carbonferret/__init__.py
carbonferret/core.py
carbonferret/tests/__init__.py
carbonferret/tests/test_carbonferret.py
carbonferret-0.0.1.dist-info/DESCRIPTION.rst
carbonferret-0.0.1.dist-info/METADATA
carbonferret-0.0.1.dist-info/RECORD
carbonferret-0.0.1.dist-info/WHEEL
carbonferret-0.0.1.dist-info/metadata.json
carbonferret-0.0.1.dist-info/top_level.txt
