Metadata-Version: 2.0
Name: carbonferret
Version: 0.0.1
Summary: Use Python to quickly query carbon reservoir records at http://calib.org/marine/
Home-page: https://github.com/brews/carbonferret
Author: S. Brewster Malevich
Author-email: malevich@email.arizona.edu
License: GPLv3
Keywords: marine carbonreservoir c14
Platform: UNKNOWN
Classifier: Development Status :: 3 - Alpha
Classifier: Intended Audience :: Developers
Classifier: Intended Audience :: Science/Research
Classifier: Topic :: Scientific/Engineering
Classifier: Topic :: Software Development
Classifier: License :: OSI Approved :: GNU General Public License v3 or later (GPLv3+)
Classifier: Programming Language :: Python :: 3
Requires-Dist: beautifulsoup4
Requires-Dist: html5lib
Requires-Dist: lxml
Requires-Dist: pandas
Requires-Dist: requests
Provides-Extra: dev
Requires-Dist: check-manifest; extra == 'dev'
